igthon/__init__.py
igthon/automation.py
igthon/scraping.py
igthon/utils.py
igthon-1.0.0.dist-info/licenses/LICENSE
igthon-1.0.0.dist-info/METADATA
igthon-1.0.0.dist-info/WHEEL
igthon-1.0.0.dist-info/top_level.txt
igthon-1.0.0.dist-info/RECORD
