Metadata-Version: 2.4
Name: igthon
Version: 1.0.0
Summary: Library Python untuk Instagram
Home-page: https://github.com/ivan732/InstaPy
Author: ivan
Keywords: instagram api library
Classifier: Programming Language :: Python :: 3
Classifier: License :: OSI Approved :: MIT License
Classifier: Operating System :: OS Independent
Requires-Python: >=3.6
License-File: LICENSE
Requires-Dist: requests
Dynamic: author
Dynamic: classifier
Dynamic: description
Dynamic: description-content-type
Dynamic: home-page
Dynamic: keywords
Dynamic: license-file
Dynamic: requires-dist
Dynamic: requires-python
Dynamic: summary
